makekml3/__init__.py
makekml3-0.2.1.dist-info/METADATA
makekml3-0.2.1.dist-info/RECORD
makekml3-0.2.1.dist-info/WHEEL
makekml3-0.2.1.dist-info/top_level.txt
