Metadata-Version: 2.1
Name: makekml3
Version: 0.2.1
Summary: This is a library designed to create kml. it also has a number of useful features, such as getting the intersection and union of polygons etc
Home-page: UNKNOWN
Author: Steve Mohr
Author-email: steve.h.mohr@gmail.com
License: UNKNOWN
Platform: UNKNOWN
